setup.py
ankush_test.egg-info/PKG-INFO
ankush_test.egg-info/SOURCES.txt
ankush_test.egg-info/dependency_links.txt
ankush_test.egg-info/not-zip-safe
ankush_test.egg-info/top_level.txt
distributions/Binomialdistribution.py
distributions/Gaussiandistribution.py
distributions/Generaldistribution.py
distributions/__init__.py