Metadata-Version: 1.0
Name: ankush-test
Version: 0.1
Summary: Gaussian distributions
Home-page: UNKNOWN
Author: Ankush Anshuman
Author-email: ankush3107@gmail.com
License: UNKNOWN
Platform: UNKNOWN
